p1_queue/__init__.py
p1_queue/base_consumer.py
p1_queue/publisher.py
p1_queue/v2/__init__.py
p1_queue/v2/base_consumer.py
p1_queue/v2/base_publisher.py
p1_queue-0.4.3.dist-info/METADATA
p1_queue-0.4.3.dist-info/WHEEL
p1_queue-0.4.3.dist-info/top_level.txt
p1_queue-0.4.3.dist-info/RECORD
