Metadata-Version: 2.4
Name: p1-queue
Version: 0.4.3
Summary: Messaging abstraction for AMQP
Author: Turfa Auliarachman
Author-email: turfa_auliarachman@rocketmail.com
License: MIT
Classifier: Intended Audience :: Developers
Classifier: Programming Language :: Python :: 2
Classifier: Programming Language :: Python :: 3
Requires-Dist: pika==1.3.2
Requires-Dist: google-cloud-pubsub==2.19.0
Requires-Dist: tornado==6.4
Dynamic: author
Dynamic: author-email
Dynamic: classifier
Dynamic: description
Dynamic: description-content-type
Dynamic: license
Dynamic: requires-dist
Dynamic: summary
